echidnalib/__init__.py
echidnalib/bot_core.py
echidnalib-0.0.4.dist-info/LICENSE
echidnalib-0.0.4.dist-info/METADATA
echidnalib-0.0.4.dist-info/WHEEL
echidnalib-0.0.4.dist-info/top_level.txt
echidnalib-0.0.4.dist-info/RECORD
