Metadata-Version: 2.1
Name: echidnalib
Version: 0.0.4
Summary: A modular discord bot package
Home-page: https://github.com/IdleEchidna/EchidnaLib
Author: IdleEchidna
Author-email: 
License: UNKNOWN
Project-URL: Bug Tracker, https://github.com/IdleEchidna/EchidnaLib/issues
Platform: UNKNOWN
Classifier: Programming Language :: Python :: 3
Classifier: License :: OSI Approved :: MIT License
Classifier: Operating System :: OS Independent
Requires-Python: >=3.6
